setup.py
common_stats_distributions/Binomialdistribution.py
common_stats_distributions/Gaussiandistribution.py
common_stats_distributions/Generaldistribution.py
common_stats_distributions/__init__.py
common_stats_distributions.egg-info/PKG-INFO
common_stats_distributions.egg-info/SOURCES.txt
common_stats_distributions.egg-info/dependency_links.txt
common_stats_distributions.egg-info/not-zip-safe
common_stats_distributions.egg-info/top_level.txt