Metadata-Version: 1.0
Name: common-stats-distributions
Version: 0.1
Summary: Gaussian and binomial distributions
Home-page: UNKNOWN
Author: Chaojie Wang
Author-email: UNKNOWN
License: UNKNOWN
Platform: UNKNOWN
